dislash/__init__.py
dislash/application_commands/__init__.py
dislash/application_commands/_decohub.py
dislash/application_commands/context_menus_core.py
dislash/application_commands/core.py
dislash/application_commands/errors.py
dislash/application_commands/slash_client.py
dislash/application_commands/slash_core.py
dislash/application_commands/utils.py
dislash/application_commands/_modifications/__init__.py
dislash/application_commands/_modifications/new.py
dislash/application_commands/_modifications/old.py
dislash/interactions/__init__.py
dislash/interactions/app_command_interaction.py
dislash/interactions/application_command.py
dislash/interactions/interaction.py
dislash/interactions/message_components.py
dislash/interactions/message_interaction.py
dislash/interactions/slash_interaction.py
dislash/slash_commands/__init__.py
dislash/slash_commands/_decohub.py
dislash/slash_commands/errors.py
dislash/slash_commands/slash_client.py
dislash/slash_commands/slash_command.py
dislash/slash_commands/slash_core.py
dislash/slash_commands/utils.py
dislash/slash_commands/_modifications/__init__.py
dislash/slash_commands/_modifications/new.py
dislash/slash_commands/_modifications/old.py
dislash.py-1.4.9.dist-info/LICENSE
dislash.py-1.4.9.dist-info/METADATA
dislash.py-1.4.9.dist-info/WHEEL
dislash.py-1.4.9.dist-info/top_level.txt
dislash.py-1.4.9.dist-info/RECORD
