Metadata-Version: 2.1
Name: dislash.py
Version: 1.4.9
Summary: A python wrapper for message components and application commands.
Home-page: https://github.com/EQUENOS/dislash.py
Author: EQUENOS
Author-email: equenos1@gmail.com
License: MIT
Project-URL: Documentation, https://dislashpy.readthedocs.io/en/latest
Project-URL: Bug Reports, https://github.com/EQUENOS/dislash.py/issues
Project-URL: Source, https://github.com/EQUENOS/dislash.py
Keywords: python,discord,slash,commands,api,discord-api,discord-py,slash-commands,message-components,buttons,select-menus,context-menus
Platform: UNKNOWN
Classifier: License :: OSI Approved :: MIT License
Classifier: Intended Audience :: Developers
Classifier: Natural Language :: English
Classifier: Operating System :: OS Independent
Classifier: Programming Language :: Python :: 3.6
Classifier: Programming Language :: Python :: 3.7
Classifier: Programming Language :: Python :: 3.8
Classifier: Programming Language :: Python :: 3.9
Classifier: Topic :: Internet
Classifier: Topic :: Software Development :: Libraries
Classifier: Topic :: Software Development :: Libraries :: Python Modules
Classifier: Topic :: Utilities
Requires-Python: >=3.6, <4
License-File: LICENSE
